
{
  "header": {
    "reportVersion": 1,
    "event": "Allocation failed - JavaScript heap out of memory",
    "trigger": "FatalError",
    "filename": "report.20201105.022904.2572.0.001.json",
    "dumpEventTime": "2020-11-05T02:29:04Z",
    "dumpEventTimeStamp": "1604532544990",
    "processId": 2572,
    "cwd": "D:\\Работа\\Верстка\\2020\\anadyry",
    "commandLine": [
      "node",
      "C:\\Users\\Алексей Миура\\AppData\\Roaming\\npm\\\\node_modules\\gulp\\bin\\gulp.js"
    ],
    "nodejsVersion": "v12.16.1",
    "wordSize": 64,
    "arch": "x64",
    "platform": "win32",
    "componentVersions": {
      "node": "12.16.1",
      "v8": "7.8.279.23-node.31",
      "uv": "1.34.0",
      "zlib": "1.2.11",
      "brotli": "1.0.7",
      "ares": "1.15.0",
      "modules": "72",
      "nghttp2": "1.40.0",
      "napi": "5",
      "llhttp": "2.0.4",
      "http_parser": "2.9.3",
      "openssl": "1.1.1d",
      "cldr": "35.1",
      "icu": "64.2",
      "tz": "2019c",
      "unicode": "12.1"
    },
    "release": {
      "name": "node",
      "lts": "Erbium",
      "headersUrl": "https://nodejs.org/download/release/v12.16.1/node-v12.16.1-headers.tar.gz",
      "sourceUrl": "https://nodejs.org/download/release/v12.16.1/node-v12.16.1.tar.gz",
      "libUrl": "https://nodejs.org/download/release/v12.16.1/win-x64/node.lib"
    },
    "osName": "Windows_NT",
    "osRelease": "10.0.18363",
    "osVersion": "Windows 10 Pro",
    "osMachine": "x86_64",
    "cpus": [
      {
        "model": "Intel(R) Core(TM) i7-7700HQ CPU @ 2.80GHz",
        "speed": 2808,
        "user": 1765765,
        "nice": 0,
        "sys": 1013781,
        "idle": 5006156,
        "irq": 92765
      },
      {
        "model": "Intel(R) Core(TM) i7-7700HQ CPU @ 2.80GHz",
        "speed": 2808,
        "user": 2337640,
        "nice": 0,
        "sys": 937750,
        "idle": 4510093,
        "irq": 24328
      },
      {
        "model": "Intel(R) Core(TM) i7-7700HQ CPU @ 2.80GHz",
        "speed": 2808,
        "user": 2084296,
        "nice": 0,
        "sys": 791937,
        "idle": 4909250,
        "irq": 15031
      },
      {
        "model": "Intel(R) Core(TM) i7-7700HQ CPU @ 2.80GHz",
        "speed": 2808,
        "user": 2340109,
        "nice": 0,
        "sys": 717281,
        "idle": 4728093,
        "irq": 12578
      }
    ],
    "networkInterfaces": [
      {
        "name": "Ethernet",
        "internal": false,
        "mac": "4c:cc:6a:de:fe:9a",
        "address": "fd01::f003:b1ee:a878:f077",
        "netmask": "ffff:ffff:ffff:ffff::",
        "family": "IPv6",
        "scopeid": 0
      },
      {
        "name": "Ethernet",
        "internal": false,
        "mac": "4c:cc:6a:de:fe:9a",
        "address": "fd01::2588:a511:8737:cd0",
        "netmask": "ffff:ffff:ffff:ffff:ffff:ffff:ffff:ffff",
        "family": "IPv6",
        "scopeid": 0
      },
      {
        "name": "Ethernet",
        "internal": false,
        "mac": "4c:cc:6a:de:fe:9a",
        "address": "fe80::f003:b1ee:a878:f077",
        "netmask": "ffff:ffff:ffff:ffff::",
        "family": "IPv6",
        "scopeid": 12
      },
      {
        "name": "Ethernet",
        "internal": false,
        "mac": "4c:cc:6a:de:fe:9a",
        "address": "192.168.0.42",
        "netmask": "255.255.255.0",
        "family": "IPv4"
      },
      {
        "name": "Loopback Pseudo-Interface 1",
        "internal": true,
        "mac": "00:00:00:00:00:00",
        "address": "::1",
        "netmask": "ffff:ffff:ffff:ffff:ffff:ffff:ffff:ffff",
        "family": "IPv6",
        "scopeid": 0
      },
      {
        "name": "Loopback Pseudo-Interface 1",
        "internal": true,
        "mac": "00:00:00:00:00:00",
        "address": "127.0.0.1",
        "netmask": "255.0.0.0",
        "family": "IPv4"
      }
    ],
    "host": "DESKTOP-DR6J7UJ"
  },
  "javascriptStack": {
    "message": "No stack.",
    "stack": [
      "Unavailable."
    ]
  },
  "nativeStack": [
    {
      "pc": "0x00007ff685ef19f9",
      "symbol": "std::basic_ostream<char,std::char_traits<char> >::operator<<+10873"
    },
    {
      "pc": "0x00007ff685ef5e1c",
      "symbol": "std::basic_ostream<char,std::char_traits<char> >::operator<<+28316"
    },
    {
      "pc": "0x00007ff685ef4dd8",
      "symbol": "std::basic_ostream<char,std::char_traits<char> >::operator<<+24152"
    },
    {
      "pc": "0x00007ff685ff34cb",
      "symbol": "v8::base::CPU::has_sse+38363"
    },
    {
      "pc": "0x00007ff686809f4e",
      "symbol": "v8::Isolate::ReportExternalAllocationLimitReached+94"
    },
    {
      "pc": "0x00007ff6867f2021",
      "symbol": "v8::SharedArrayBuffer::Externalize+833"
    },
    {
      "pc": "0x00007ff6866be57c",
      "symbol": "v8::internal::Heap::EphemeronKeyWriteBarrierFromCode+1436"
    },
    {
      "pc": "0x00007ff6866c97d0",
      "symbol": "v8::internal::Heap::ProtectUnprotectedMemoryChunks+1312"
    },
    {
      "pc": "0x00007ff6866c62f4",
      "symbol": "v8::internal::Heap::PageFlagsAreConsistent+3204"
    },
    {
      "pc": "0x00007ff6866bbb13",
      "symbol": "v8::internal::Heap::CollectGarbage+1283"
    },
    {
      "pc": "0x00007ff6866ba184",
      "symbol": "v8::internal::Heap::AddRetainedMap+2452"
    },
    {
      "pc": "0x00007ff6866db36d",
      "symbol": "v8::internal::Factory::NewFillerObject+61"
    },
    {
      "pc": "0x00007ff686440c51",
      "symbol": "v8::internal::interpreter::JumpTableTargetOffsets::iterator::operator=+1665"
    },
    {
      "pc": "0x00007ff686c54ddd",
      "symbol": "v8::internal::SetupIsolateDelegate::SetupHeap+546637"
    },
    {
      "pc": "0x00007ff686c55d0d",
      "symbol": "v8::internal::SetupIsolateDelegate::SetupHeap+550525"
    },
    {
      "pc": "0x000001d73aafaf67",
      "symbol": ""
    }
  ],
  "javascriptHeap": {
    "totalMemory": 2153758720,
    "totalCommittedMemory": 2153758720,
    "usedMemory": 2129219392,
    "availableMemory": 58210704,
    "memoryLimit": 2197815296,
    "heapSpaces": {
      "read_only_space": {
        "memorySize": 262144,
        "committedMemory": 262144,
        "capacity": 32808,
        "used": 32808,
        "available": 0
      },
      "new_space": {
        "memorySize": 4194304,
        "committedMemory": 4194304,
        "capacity": 2094912,
        "used": 182536,
        "available": 1912376
      },
      "old_space": {
        "memorySize": 2016034816,
        "committedMemory": 2016034816,
        "capacity": 2007347992,
        "used": 1997201152,
        "available": 10146840
      },
      "code_space": {
        "memorySize": 2265088,
        "committedMemory": 2265088,
        "capacity": 1817824,
        "used": 1817824,
        "available": 0
      },
      "map_space": {
        "memorySize": 3149824,
        "committedMemory": 3149824,
        "capacity": 2286960,
        "used": 2286960,
        "available": 0
      },
      "large_object_space": {
        "memorySize": 127229952,
        "committedMemory": 127229952,
        "capacity": 127153824,
        "used": 127153824,
        "available": 0
      },
      "code_large_object_space": {
        "memorySize": 622592,
        "committedMemory": 622592,
        "capacity": 544288,
        "used": 544288,
        "available": 0
      },
      "new_large_object_space": {
        "memorySize": 0,
        "committedMemory": 0,
        "capacity": 2094912,
        "used": 0,
        "available": 2094912
      }
    }
  },
  "resourceUsage": {
    "userCpuSeconds": 2128.84,
    "kernelCpuSeconds": 1097.81,
    "cpuConsumptionPercent": 41.8937,
    "maxRss": 3911565312,
    "pageFaults": {
      "IORequired": 11701312,
      "IONotRequired": 0
    },
    "fsActivity": {
      "reads": 132195,
      "writes": 1660
    }
  },
  "libuv": [
  ],
  "environmentVariables": {
    "=D:": "D:\\Работа\\Верстка\\2020\\anadyry",
    "dp0": "C:\\Users\\Алексей Миура\\AppData\\Roaming\\npm\\",
    "FPS_BROWSER_APP_PROFILE_STRING": "Internet Explorer",
    "CommonProgramFiles": "C:\\Program Files\\Common Files",
    "INIT_CWD": "D:\\Работа\\Верстка\\2020\\anadyry",
    "PROMPT": "$P$G",
    "SESSIONNAME": "Console",
    "ChocolateyInstall": "C:\\ProgramData\\chocolatey",
    "_prog": "node",
    "__INTELLIJ_COMMAND_HISTFILE__": "C:\\Users\\Алексей Миура\\.PhpStorm2019.3\\config\\terminal\\history\\history-484",
    "SystemDrive": "C:",
    "NUMBER_OF_PROCESSORS": "4",
    "LOGONSERVER": "\\\\DESKTOP-DR6J7UJ",
    "TEMP": "C:\\Users\\0959~1\\AppData\\Local\\Temp",
    "TMP": "C:\\Users\\0959~1\\AppData\\Local\\Temp",
    "HOMEPATH": "\\Users\\Алексей Миура",
    "PATHEXT": ".COM;.EXE;.BAT;.CMD;.VBS;.VBE;.JSE;.WSF;.WSH;.MSC;.RB;.RBW",
    "IDEA_INITIAL_DIRECTORY": "C:\\Program Files\\JetBrains\\PhpStorm 2019.3.4\\bin",
    "=::": "::\\",
    "USERNAME": "Алексей Миура",
    "ProgramFiles": "C:\\Program Files",
    "USERDOMAIN_ROAMINGPROFILE": "DESKTOP-DR6J7UJ",
    "LOCALAPPDATA": "C:\\Users\\Алексей Миура\\AppData\\Local",
    "TERMINAL_EMULATOR": "JetBrains-JediTerm",
    "ProgramData": "C:\\ProgramData",
    "PROCESSOR_IDENTIFIER": "Intel64 Family 6 Model 158 Stepping 9, GenuineIntel",
    "DriverData": "C:\\Windows\\System32\\Drivers\\DriverData",
    "APPDATA": "C:\\Users\\Алексей Миура\\AppData\\Roaming",
    "HOMEDRIVE": "C:",
    "ALLUSERSPROFILE": "C:\\ProgramData",
    "USERDOMAIN": "DESKTOP-DR6J7UJ",
    "RUBYOPT": "-Eutf-8",
    "PROCESSOR_LEVEL": "6",
    "ChocolateyLastPathUpdate": "132295080582670344",
    "ComSpec": "C:\\Windows\\system32\\cmd.exe",
    "PROCESSOR_ARCHITECTURE": "AMD64",
    "FPS_BROWSER_USER_PROFILE_STRING": "Default",
    "SystemRoot": "C:\\Windows",
    "PhpStorm": "C:\\Program Files\\JetBrains\\PhpStorm 2019.3.4\\bin;",
    "PROCESSOR_REVISION": "9e09",
    "OneDrive": "C:\\Users\\Алексей Миура\\OneDrive",
    "PSModulePath": "C:\\Program Files\\WindowsPowerShell\\Modules;C:\\Windows\\system32\\WindowsPowerShell\\v1.0\\Modules",
    "PATH": "D:\\Работа\\Верстка\\2020\\anadyry\\node_modules\\.bin;C:\\Python27\\;C:\\Python27\\Scripts;c:\\program files (x86)\\intel\\intel(r) management engine components\\icls\\;c:\\program files\\intel\\intel(r) management engine components\\icls\\;c:\\windows\\system32;c:\\windows;c:\\windows\\system32\\wbem;c:\\windows\\system32\\windowspowershell\\v1.0\\;c:\\windows\\system32\\openssh\\;c:\\program files (x86)\\intel\\intel(r) management engine components\\dal;c:\\program files\\intel\\intel(r) management engine components\\dal;c:\\program files (x86)\\intel\\intel(r) management engine components\\ipt;c:\\program files\\intel\\intel(r) management engine components\\ipt;c:\\program files\\intel\\wifi\\bin\\;c:\\program files\\common files\\intel\\wirelesscommon\\;c:\\program files\\putty\\;c:\\program files\\nvidia corporation\\nvidia nvdlisr;C:\\Program Files (x86)\\NVIDIA Corporation\\PhysX\\Common;C:\\Program Files\\nodejs\\;C:\\ProgramData\\chocolatey\\bin;C:\\Program Files (x86)\\Yarn\\bin\\;C:\\Program Files\\Git\\cmd;C:\\Ruby26-x64\\bin;C:\\Users\\Алексей Миура\\AppData\\Local\\Microsoft\\WindowsApps;C:\\Program Files\\Intel\\WiFi\\bin\\;C:\\Program Files\\Common Files\\Intel\\WirelessCommon\\;C:\\Program Files\\JetBrains\\PhpStorm 2019.3.4\\bin;;C:\\Users\\Алексей Миура\\AppData\\Roaming\\npm;C:\\Users\\Алексей Миура\\AppData\\Local\\Yarn\\bin",
    "ProgramFiles(x86)": "C:\\Program Files (x86)",
    "USERPROFILE": "C:\\Users\\Алексей Миура",
    "windir": "C:\\Windows",
    "ProgramW6432": "C:\\Program Files",
    "OS": "Windows_NT",
    "CommonProgramFiles(x86)": "C:\\Program Files (x86)\\Common Files",
    "PUBLIC": "C:\\Users\\Public",
    "COMPUTERNAME": "DESKTOP-DR6J7UJ",
    "CommonProgramW6432": "C:\\Program Files\\Common Files"
  },
  "sharedObjects": [
    "C:\\Program Files\\nodejs\\node.exe",
    "C:\\Windows\\SYSTEM32\\ntdll.dll",
    "C:\\Windows\\System32\\KERNEL32.DLL",
    "C:\\Windows\\System32\\KERNELBASE.dll",
    "C:\\Windows\\System32\\WS2_32.dll",
    "C:\\Windows\\System32\\RPCRT4.dll",
    "C:\\Windows\\System32\\PSAPI.DLL",
    "C:\\Windows\\System32\\ADVAPI32.dll",
    "C:\\Windows\\System32\\msvcrt.dll",
    "C:\\Windows\\System32\\sechost.dll",
    "C:\\Windows\\System32\\USER32.dll",
    "C:\\Windows\\System32\\win32u.dll",
    "C:\\Windows\\System32\\GDI32.dll",
    "C:\\Windows\\System32\\gdi32full.dll",
    "C:\\Windows\\System32\\msvcp_win.dll",
    "C:\\Windows\\System32\\ucrtbase.dll",
    "C:\\Windows\\System32\\CRYPT32.dll",
    "C:\\Windows\\SYSTEM32\\dbghelp.dll",
    "C:\\Windows\\System32\\MSASN1.dll",
    "C:\\Windows\\System32\\bcrypt.dll",
    "C:\\Windows\\SYSTEM32\\IPHLPAPI.DLL",
    "C:\\Windows\\SYSTEM32\\USERENV.dll",
    "C:\\Windows\\System32\\profapi.dll",
    "C:\\Windows\\SYSTEM32\\WINMM.dll",
    "C:\\Windows\\SYSTEM32\\winmmbase.dll",
    "C:\\Windows\\System32\\cfgmgr32.dll",
    "C:\\Windows\\System32\\bcryptPrimitives.dll",
    "C:\\Windows\\System32\\IMM32.DLL",
    "C:\\Windows\\System32\\powrprof.dll",
    "C:\\Windows\\System32\\UMPDC.dll",
    "C:\\Windows\\SYSTEM32\\CRYPTBASE.DLL",
    "C:\\Windows\\system32\\uxtheme.dll",
    "C:\\Windows\\System32\\combase.dll",
    "C:\\Windows\\system32\\mswsock.dll",
    "C:\\Windows\\System32\\kernel.appcore.dll",
    "\\\\?\\D:\\Работа\\Верстка\\2020\\anadyry\\node_modules\\node-sass\\vendor\\win32-x64-72\\binding.node",
    "C:\\Windows\\System32\\NSI.dll",
    "C:\\Windows\\SYSTEM32\\dhcpcsvc6.DLL",
    "C:\\Windows\\SYSTEM32\\dhcpcsvc.DLL",
    "C:\\Windows\\SYSTEM32\\DNSAPI.dll",
    "C:\\Windows\\system32\\napinsp.dll",
    "C:\\Windows\\system32\\pnrpnsp.dll",
    "C:\\Windows\\System32\\winrnr.dll",
    "C:\\Windows\\system32\\NLAapi.dll",
    "C:\\Windows\\system32\\wshbth.dll"
  ]
}